{
  "data": {
    "type": "monster-drop",
    "id": "5220003",
    "attributes": {
      "drops": [
        {
          "itemId": 0,
          "minimumQuantity": 630,
          "maximumQuantity": 3090,
          "questId": 0,
          "chance": 400000
        },
        {
          "itemId": 1302011,
          "minimumQuantity": 1,
          "maximumQuantity": 1,
          "questId": 0,
          "chance": 7000
        },
        {
          "itemId": 1312009,
          "minimumQuantity": 1,
          "maximumQuantity": 1,
          "questId": 0,
          "chance": 7000
        },
        {
          "itemId": 1322018,
          "minimumQuantity": 1,
          "maximumQuantity": 1,
          "questId": 0,
          "chance": 7000
        },
        {
          "itemId": 1332015,
          "minimumQuantity": 1,
          "maximumQuantity": 1,
          "questId": 0,
          "chance": 5000
        },
        {
          "itemId": 1332017,
          "minimumQuantity": 1,
          "maximumQuantity": 1,
          "questId": 0,
          "chance": 5000
        },
        {
          "itemId": 1372014,
          "minimumQuantity": 1,
          "maximumQuantity": 1,
          "questId": 0,
          "chance": 7000
        },
        {
          "itemId": 1372033,
          "minimumQuantity": 1,
          "maximumQuantity": 1,
          "questId": 0,
          "chance": 7000
        },
        {
          "itemId": 1382007,
          "minimumQuantity": 1,
          "maximumQuantity": 1,
          "questId": 0,
          "chance": 7000
        },
        {
          "itemId": 1402011,
          "minimumQuantity": 1,
          "maximumQuantity": 1,
          "questId": 0,
          "chance": 7000
        },
        {
          "itemId": 1412007,
          "minimumQuantity": 1,
          "maximumQuantity": 1,
          "questId": 0,
          "chance": 7000
        },
        {
          "itemId": 1422009,
          "minimumQuantity": 1,
          "maximumQuantity": 1,
          "questId": 0,
          "chance": 7000
        },
        {
          "itemId": 1432006,
          "minimumQuantity": 1,
          "maximumQuantity": 1,
          "questId": 0,
          "chance": 5000
        },
        {
          "itemId": 1442010,
          "minimumQuantity": 1,
          "maximumQuantity": 1,
          "questId": 0,
          "chance": 7000
        },
        {
          "itemId": 1452004,
          "minimumQuantity": 1,
          "maximumQuantity": 1,
          "questId": 0,
          "chance": 5000
        },
        {
          "itemId": 1462008,
          "minimumQuantity": 1,
          "maximumQuantity": 1,
          "questId": 0,
          "chance": 5000
        },
        {
          "itemId": 1472025,
          "minimumQuantity": 1,
          "maximumQuantity": 1,
          "questId": 0,
          "chance": 5000
        },
        {
          "itemId": 1482008,
          "minimumQuantity": 1,
          "maximumQuantity": 1,
          "questId": 0,
          "chance": 5000
        },
        {
          "itemId": 1492008,
          "minimumQuantity": 1,
          "maximumQuantity": 1,
          "questId": 0,
          "chance": 5000
        },
        {
          "itemId": 1492022,
          "minimumQuantity": 1,
          "maximumQuantity": 1,
          "questId": 0,
          "chance": 1250
        },
        {
          "itemId": 2000002,
          "minimumQuantity": 1,
          "maximumQuantity": 1,
          "questId": 0,
          "chance": 200000
        },
        {
          "itemId": 2000003,
          "minimumQuantity": 1,
          "maximumQuantity": 1,
          "questId": 0,
          "chance": 200000
        },
        {
          "itemId": 2002002,
          "minimumQuantity": 1,
          "maximumQuantity": 1,
          "questId": 0,
          "chance": 200000
        },
        {
          "itemId": 2002003,
          "minimumQuantity": 1,
          "maximumQuantity": 1,
          "questId": 0,
          "chance": 200000
        },
        {
          "itemId": 2040302,
          "minimumQuantity": 1,
          "maximumQuantity": 1,
          "questId": 0,
          "chance": 3000
        },
        {
          "itemId": 2040401,
          "minimumQuantity": 1,
          "maximumQuantity": 1,
          "questId": 0,
          "chance": 3000
        },
        {
          "itemId": 2040502,
          "minimumQuantity": 1,
          "maximumQuantity": 1,
          "questId": 0,
          "chance": 3000
        },
        {
          "itemId": 2040516,
          "minimumQuantity": 1,
          "maximumQuantity": 1,
          "questId": 0,
          "chance": 3000
        },
        {
          "itemId": 2040614,
          "minimumQuantity": 1,
          "maximumQuantity": 4,
          "questId": 0,
          "chance": 10000
        },
        {
          "itemId": 2040627,
          "minimumQuantity": 1,
          "maximumQuantity": 1,
          "questId": 0,
          "chance": 3000
        },
        {
          "itemId": 2040704,
          "minimumQuantity": 1,
          "maximumQuantity": 1,
          "questId": 0,
          "chance": 3000
        },
        {
          "itemId": 2040804,
          "minimumQuantity": 1,
          "maximumQuantity": 1,
          "questId": 0,
          "chance": 3000
        },
        {
          "itemId": 2040825,
          "minimumQuantity": 1,
          "maximumQuantity": 1,
          "questId": 0,
          "chance": 3000
        },
        {
          "itemId": 2040933,
          "minimumQuantity": 1,
          "maximumQuantity": 1,
          "questId": 0,
          "chance": 3000
        },
        {
          "itemId": 2041002,
          "minimumQuantity": 1,
          "maximumQuantity": 1,
          "questId": 0,
          "chance": 3000
        },
        {
          "itemId": 2041013,
          "minimumQuantity": 1,
          "maximumQuantity": 1,
          "questId": 0,
          "chance": 3000
        },
        {
          "itemId": 2041016,
          "minimumQuantity": 1,
          "maximumQuantity": 1,
          "questId": 0,
          "chance": 3000
        },
        {
          "itemId": 2041046,
          "minimumQuantity": 1,
          "maximumQuantity": 4,
          "questId": 0,
          "chance": 10000
        },
        {
          "itemId": 2043201,
          "minimumQuantity": 1,
          "maximumQuantity": 1,
          "questId": 0,
          "chance": 3000
        },
        {
          "itemId": 2043701,
          "minimumQuantity": 1,
          "maximumQuantity": 1,
          "questId": 0,
          "chance": 3000
        },
        {
          "itemId": 2043802,
          "minimumQuantity": 1,
          "maximumQuantity": 1,
          "questId": 0,
          "chance": 3000
        },
        {
          "itemId": 2044114,
          "minimumQuantity": 1,
          "maximumQuantity": 1,
          "questId": 0,
          "chance": 3000
        },
        {
          "itemId": 2044116,
          "minimumQuantity": 1,
          "maximumQuantity": 4,
          "questId": 0,
          "chance": 10000
        },
        {
          "itemId": 2044201,
          "minimumQuantity": 1,
          "maximumQuantity": 1,
          "questId": 0,
          "chance": 3000
        },
        {
          "itemId": 2044301,
          "minimumQuantity": 1,
          "maximumQuantity": 1,
          "questId": 0,
          "chance": 3000
        },
        {
          "itemId": 2044502,
          "minimumQuantity": 1,
          "maximumQuantity": 1,
          "questId": 0,
          "chance": 3000
        },
        {
          "itemId": 2044801,
          "minimumQuantity": 1,
          "maximumQuantity": 1,
          "questId": 0,
          "chance": 3000
        },
        {
          "itemId": 2044803,
          "minimumQuantity": 1,
          "maximumQuantity": 4,
          "questId": 0,
          "chance": 10000
        },
        {
          "itemId": 2044807,
          "minimumQuantity": 1,
          "maximumQuantity": 1,
          "questId": 0,
          "chance": 3000
        },
        {
          "itemId": 2044902,
          "minimumQuantity": 1,
          "maximumQuantity": 1,
          "questId": 0,
          "chance": 3000
        },
        {
          "itemId": 2044904,
          "minimumQuantity": 1,
          "maximumQuantity": 4,
          "questId": 0,
          "chance": 10000
        },
        {
          "itemId": 2060000,
          "minimumQuantity": 107,
          "maximumQuantity": 134,
          "questId": 0,
          "chance": 300000
        },
        {
          "itemId": 2061000,
          "minimumQuantity": 107,
          "maximumQuantity": 134,
          "questId": 0,
          "chance": 300000
        },
        {
          "itemId": 2388005,
          "minimumQuantity": 1,
          "maximumQuantity": 1,
          "questId": 0,
          "chance": 24000
        },
        {
          "itemId": 4000113,
          "minimumQuantity": 1,
          "maximumQuantity": 1,
          "questId": 0,
          "chance": 600000
        },
        {
          "itemId": 4000114,
          "minimumQuantity": 1,
          "maximumQuantity": 1,
          "questId": 0,
          "chance": 600000
        },
        {
          "itemId": 4000115,
          "minimumQuantity": 1,
          "maximumQuantity": 1,
          "questId": 0,
          "chance": 600000
        },
        {
          "itemId": 4004001,
          "minimumQuantity": 1,
          "maximumQuantity": 1,
          "questId": 0,
          "chance": 100000
        },
        {
          "itemId": 4010003,
          "minimumQuantity": 1,
          "maximumQuantity": 1,
          "questId": 0,
          "chance": 90000
        },
        {
          "itemId": 4020006,
          "minimumQuantity": 1,
          "maximumQuantity": 1,
          "questId": 0,
          "chance": 90000
        },
        {
          "itemId": 4031991,
          "minimumQuantity": 1,
          "maximumQuantity": 1,
          "questId": 3248,
          "chance": 999999
        }
      ]
    }
  }
}
