{
  "WriterName": "ChatSetAvatarMegaphone",
  "IDAName": "CWvsContext::OnSetAvatarMegaphone",
  "Address": "0xa2a486",
  "Variant": "GMS/v83",
  "BranchDepth": 0,
  "AtlasFile": "libs/atlas-packet/chat/clientbound/avatar_megaphone.go",
  "Rows": [
    {
      "Index": 0,
      "AtlasOp": 2,
      "AtlasKind": 0,
      "IDAOp": 2,
      "IDAComment": "itemId",
      "Verdict": 0,
      "Note": ""
    },
    {
      "Index": 1,
      "AtlasOp": 4,
      "AtlasKind": 0,
      "IDAOp": 4,
      "IDAComment": "name (sender name)",
      "Verdict": 0,
      "Note": ""
    },
    {
      "Index": 2,
      "AtlasOp": 4,
      "AtlasKind": 0,
      "IDAOp": 4,
      "IDAComment": "lines[0]",
      "Verdict": 0,
      "Note": ""
    },
    {
      "Index": 3,
      "AtlasOp": 2,
      "AtlasKind": 0,
      "IDAOp": 4,
      "IDAComment": "lines[1]",
      "Verdict": 2,
      "Note": "width mismatch"
    },
    {
      "Index": 4,
      "AtlasOp": 0,
      "AtlasKind": 0,
      "IDAOp": 4,
      "IDAComment": "lines[2]",
      "Verdict": 2,
      "Note": "width mismatch"
    },
    {
      "Index": 5,
      "AtlasOp": 0,
      "AtlasKind": 0,
      "IDAOp": 4,
      "IDAComment": "lines[3]",
      "Verdict": 2,
      "Note": "width mismatch"
    },
    {
      "Index": 6,
      "AtlasOp": 0,
      "AtlasKind": 0,
      "IDAOp": 2,
      "IDAComment": "channelId",
      "Verdict": 2,
      "Note": "width mismatch"
    },
    {
      "Index": 7,
      "AtlasOp": 2,
      "AtlasKind": 0,
      "IDAOp": 0,
      "IDAComment": "whispersOn",
      "Verdict": 2,
      "Note": "width mismatch"
    },
    {
      "Index": 8,
      "AtlasOp": 0,
      "AtlasKind": 0,
      "IDAOp": 5,
      "IDAComment": "AvatarLook::Decode(look) — opaque avatar block (model.Avatar recurse)",
      "Verdict": 0,
      "Note": ""
    },
    {
      "Index": 9,
      "AtlasOp": 2,
      "AtlasKind": 0,
      "IDAOp": 0,
      "IDAComment": "",
      "Verdict": 0,
      "Note": "absorbed by trailing opaque buffer"
    },
    {
      "Index": 10,
      "AtlasOp": 0,
      "AtlasKind": 0,
      "IDAOp": 0,
      "IDAComment": "",
      "Verdict": 0,
      "Note": "absorbed by trailing opaque buffer"
    },
    {
      "Index": 11,
      "AtlasOp": 2,
      "AtlasKind": 0,
      "IDAOp": 0,
      "IDAComment": "",
      "Verdict": 0,
      "Note": "absorbed by trailing opaque buffer"
    },
    {
      "Index": 12,
      "AtlasOp": 0,
      "AtlasKind": 0,
      "IDAOp": 0,
      "IDAComment": "",
      "Verdict": 0,
      "Note": "absorbed by trailing opaque buffer"
    },
    {
      "Index": 13,
      "AtlasOp": 0,
      "AtlasKind": 0,
      "IDAOp": 0,
      "IDAComment": "",
      "Verdict": 0,
      "Note": "absorbed by trailing opaque buffer"
    },
    {
      "Index": 14,
      "AtlasOp": 2,
      "AtlasKind": 0,
      "IDAOp": 0,
      "IDAComment": "",
      "Verdict": 0,
      "Note": "absorbed by trailing opaque buffer"
    },
    {
      "Index": 15,
      "AtlasOp": 0,
      "AtlasKind": 0,
      "IDAOp": 0,
      "IDAComment": "",
      "Verdict": 0,
      "Note": "absorbed by trailing opaque buffer"
    },
    {
      "Index": 16,
      "AtlasOp": 2,
      "AtlasKind": 0,
      "IDAOp": 0,
      "IDAComment": "",
      "Verdict": 0,
      "Note": "absorbed by trailing opaque buffer"
    },
    {
      "Index": 17,
      "AtlasOp": 2,
      "AtlasKind": 0,
      "IDAOp": 0,
      "IDAComment": "",
      "Verdict": 0,
      "Note": "absorbed by trailing opaque buffer"
    },
    {
      "Index": 18,
      "AtlasOp": 2,
      "AtlasKind": 0,
      "IDAOp": 0,
      "IDAComment": "",
      "Verdict": 0,
      "Note": "absorbed by trailing opaque buffer"
    }
  ],
  "Verdict": 2,
  "FlatInvalid": false
}