{
  "WriterName": "PartyInviteReject",
  "IDAName": "CWvsContext::OnPartyResult#InviteReject",
  "Address": "0xa3e31c",
  "Variant": "GMS/v83",
  "BranchDepth": 0,
  "AtlasFile": "../../libs/atlas-packet/party/serverbound/invite_reject.go",
  "Rows": [
    {
      "Index": 0,
      "AtlasOp": 0,
      "AtlasKind": 0,
      "IDAOp": 0,
      "IDAComment": "mode byte (21/22/23)",
      "Verdict": 0,
      "Note": ""
    },
    {
      "Index": 1,
      "AtlasOp": 4,
      "AtlasKind": 0,
      "IDAOp": 4,
      "IDAComment": "targetName (v152)",
      "Verdict": 0,
      "Note": ""
    }
  ],
  "Verdict": 0,
  "FlatInvalid": false
}