{
  "WriterName": "SummonSpawn",
  "IDAName": "CSummonedPool::OnCreated",
  "Address": "0x95adec",
  "Variant": "GMS/v83",
  "BranchDepth": 1,
  "AtlasFile": "libs/atlas-packet/summon/clientbound/spawn.go",
  "Rows": [
    {
      "Index": 0,
      "AtlasOp": 2,
      "AtlasKind": 0,
      "IDAOp": 2,
      "IDAComment": "cid (character id) — read upstream by CUserPool::OnUserCommonPacket@0x97240c (consumed by the dispatch; pool is cid-keyed). Atlas writes it as ownerId.",
      "Verdict": 0,
      "Note": ""
    },
    {
      "Index": 1,
      "AtlasOp": 2,
      "AtlasKind": 0,
      "IDAOp": 2,
      "IDAComment": "oid (summon object id) — OnCreated@0x95ADEC Decode4@0x95ae0e; passed to the CSummoned ctor (sub_7A30A9) as the object id. (The active path's first Decode4 after the upstream cid IS the oid.)",
      "Verdict": 0,
      "Note": ""
    },
    {
      "Index": 2,
      "AtlasOp": 2,
      "AtlasKind": 0,
      "IDAOp": 2,
      "IDAComment": "skillId (nSkillID) — OnCreated@0x95ADEC Decode4@0x95ae17; consumed by GetSkill@CSkillInfo.",
      "Verdict": 0,
      "Note": ""
    },
    {
      "Index": 3,
      "AtlasOp": 0,
      "AtlasKind": 0,
      "IDAOp": 0,
      "IDAComment": "charLevel (nCharLevel) — OnCreated@0x95ADEC Decode1@0x95ae21; atlas writes fixed 0x0A (visual-only).",
      "Verdict": 0,
      "Note": ""
    },
    {
      "Index": 4,
      "AtlasOp": 0,
      "AtlasKind": 0,
      "IDAOp": 0,
      "IDAComment": "SLV skill level (nSLV) — OnCreated@0x95ADEC Decode1@0x95ae30; atlas 'level'.",
      "Verdict": 0,
      "Note": ""
    },
    {
      "Index": 5,
      "AtlasOp": 1,
      "AtlasKind": 0,
      "IDAOp": 1,
      "IDAComment": "nX — CSummoned::Init blob @0x7a379b Decode2@0x7a37b2.",
      "Verdict": 0,
      "Note": ""
    },
    {
      "Index": 6,
      "AtlasOp": 1,
      "AtlasKind": 0,
      "IDAOp": 1,
      "IDAComment": "nY — CSummoned::Init @0x7a379b Decode2@0x7a37bf.",
      "Verdict": 0,
      "Note": ""
    },
    {
      "Index": 7,
      "AtlasOp": 0,
      "AtlasKind": 0,
      "IDAOp": 0,
      "IDAComment": "nMoveAction (stance) — CSummoned::Init @0x7a379b Decode1@0x7a37cc.",
      "Verdict": 0,
      "Note": ""
    },
    {
      "Index": 8,
      "AtlasOp": 1,
      "AtlasKind": 0,
      "IDAOp": 1,
      "IDAComment": "nCurFoothold — CSummoned::Init @0x7a379b Decode2@0x7a37cf; atlas writes fixed 0 (visual-only).",
      "Verdict": 0,
      "Note": ""
    },
    {
      "Index": 9,
      "AtlasOp": 0,
      "AtlasKind": 0,
      "IDAOp": 0,
      "IDAComment": "nMoveAbility (movementType) — CSummoned::Init @0x7a379b Decode1@0x7a37e3.",
      "Verdict": 0,
      "Note": ""
    },
    {
      "Index": 10,
      "AtlasOp": 0,
      "AtlasKind": 0,
      "IDAOp": 0,
      "IDAComment": "nAssistType (!puppet attack flag) — CSummoned::Init @0x7a379b Decode1@0x7a37fa.",
      "Verdict": 0,
      "Note": ""
    },
    {
      "Index": 11,
      "AtlasOp": 0,
      "AtlasKind": 0,
      "IDAOp": 0,
      "IDAComment": "nEnterType (!animated flag; read after the Skill guard) — CSummoned::Init @0x7a379b Decode1@0x7a3821.",
      "Verdict": 0,
      "Note": ""
    },
    {
      "Index": 12,
      "AtlasOp": 0,
      "AtlasKind": 0,
      "IDAOp": 0,
      "IDAComment": "",
      "Verdict": 1,
      "Note": "atlas: trailing padding byte — client stops reading (harmless over-write)"
    }
  ],
  "Verdict": 1,
  "FlatInvalid": false
}