{
  "WriterName": "CashShopOperationMoveToCashInventory",
  "IDAName": "CCashShop::OnMoveCashItemStoL",
  "Address": "0x482b50",
  "Variant": "GMS/v95",
  "BranchDepth": 0,
  "AtlasFile": "../../libs/atlas-packet/cash/serverbound/shop_operation_move_to_cash_inventory.go",
  "Rows": [
    {
      "Index": 0,
      "AtlasOp": 3,
      "AtlasKind": 0,
      "IDAOp": 5,
      "IDAComment": "liSN 8 bytes (serialNumber uint64)",
      "Verdict": 2,
      "Note": "width mismatch"
    },
    {
      "Index": 1,
      "AtlasOp": 0,
      "AtlasKind": 0,
      "IDAOp": 0,
      "IDAComment": "nTI (inventoryType)",
      "Verdict": 0,
      "Note": ""
    }
  ],
  "Verdict": 2
}