{
  "WriterName": "ChatWorldMessageMultiMegaphone",
  "IDAName": "CWvsContext::OnBroadcastMsg#MultiMegaphone",
  "Address": "0xb0985b",
  "Variant": "JMS/v185",
  "BranchDepth": 0,
  "AtlasFile": "libs/atlas-packet/chat/clientbound/world_message.go",
  "Rows": [
    {
      "Index": 0,
      "AtlasOp": 0,
      "AtlasKind": 0,
      "IDAOp": 0,
      "IDAComment": "mode (=10, MULTI_MEGAPHONE)",
      "Verdict": 0,
      "Note": ""
    },
    {
      "Index": 1,
      "AtlasOp": 4,
      "AtlasKind": 0,
      "IDAOp": 4,
      "IDAComment": "message[0] (first message, common prefix read)",
      "Verdict": 0,
      "Note": ""
    },
    {
      "Index": 2,
      "AtlasOp": 0,
      "AtlasKind": 0,
      "IDAOp": 0,
      "IDAComment": "count byte",
      "Verdict": 0,
      "Note": ""
    },
    {
      "Index": 3,
      "AtlasOp": 4,
      "AtlasKind": 0,
      "IDAOp": 4,
      "IDAComment": "message[1]",
      "Verdict": 0,
      "Note": ""
    },
    {
      "Index": 4,
      "AtlasOp": 0,
      "AtlasKind": 0,
      "IDAOp": 4,
      "IDAComment": "message[2]",
      "Verdict": 2,
      "Note": "width mismatch"
    },
    {
      "Index": 5,
      "AtlasOp": 0,
      "AtlasKind": 0,
      "IDAOp": 0,
      "IDAComment": "channelId — shared tail with case 3",
      "Verdict": 0,
      "Note": ""
    },
    {
      "Index": 6,
      "AtlasOp": 0,
      "AtlasKind": 0,
      "IDAOp": 0,
      "IDAComment": "whispersOn",
      "Verdict": 2,
      "Note": "atlas: short — missing trailing field"
    }
  ],
  "Verdict": 3,
  "FlatInvalid": true
}