{
  "data": {
    "attributes": {
      "commodities": [
        {
          "discountRate": 0,
          "levelLimit": 0,
          "mesoPrice": 120000,
          "period": 0,
          "templateId": 1002023,
          "tokenPrice": 0,
          "tokenTemplateId": 0
        },
        {
          "discountRate": 0,
          "levelLimit": 0,
          "mesoPrice": 40000,
          "period": 0,
          "templateId": 1040021,
          "tokenPrice": 0,
          "tokenTemplateId": 0
        },
        {
          "discountRate": 0,
          "levelLimit": 0,
          "mesoPrice": 40000,
          "period": 0,
          "templateId": 1040026,
          "tokenPrice": 0,
          "tokenTemplateId": 0
        },
        {
          "discountRate": 0,
          "levelLimit": 0,
          "mesoPrice": 60000,
          "period": 0,
          "templateId": 1051010,
          "tokenPrice": 0,
          "tokenTemplateId": 0
        },
        {
          "discountRate": 0,
          "levelLimit": 0,
          "mesoPrice": 60000,
          "period": 0,
          "templateId": 1051011,
          "tokenPrice": 0,
          "tokenTemplateId": 0
        },
        {
          "discountRate": 0,
          "levelLimit": 0,
          "mesoPrice": 60000,
          "period": 0,
          "templateId": 1051012,
          "tokenPrice": 0,
          "tokenTemplateId": 0
        },
        {
          "discountRate": 0,
          "levelLimit": 0,
          "mesoPrice": 60000,
          "period": 0,
          "templateId": 1051013,
          "tokenPrice": 0,
          "tokenTemplateId": 0
        },
        {
          "discountRate": 0,
          "levelLimit": 0,
          "mesoPrice": 38000,
          "period": 0,
          "templateId": 1060016,
          "tokenPrice": 0,
          "tokenTemplateId": 0
        },
        {
          "discountRate": 0,
          "levelLimit": 0,
          "mesoPrice": 38000,
          "period": 0,
          "templateId": 1060017,
          "tokenPrice": 0,
          "tokenTemplateId": 0
        },
        {
          "discountRate": 0,
          "levelLimit": 0,
          "mesoPrice": 38000,
          "period": 0,
          "templateId": 1060018,
          "tokenPrice": 0,
          "tokenTemplateId": 0
        },
        {
          "discountRate": 0,
          "levelLimit": 0,
          "mesoPrice": 38000,
          "period": 0,
          "templateId": 1060019,
          "tokenPrice": 0,
          "tokenTemplateId": 0
        },
        {
          "discountRate": 0,
          "levelLimit": 0,
          "mesoPrice": 60000,
          "period": 0,
          "templateId": 1092006,
          "tokenPrice": 0,
          "tokenTemplateId": 0
        },
        {
          "discountRate": 0,
          "levelLimit": 0,
          "mesoPrice": 40000,
          "period": 0,
          "templateId": 1002064,
          "tokenPrice": 0,
          "tokenTemplateId": 0
        },
        {
          "discountRate": 0,
          "levelLimit": 0,
          "mesoPrice": 42000,
          "period": 0,
          "templateId": 1041041,
          "tokenPrice": 0,
          "tokenTemplateId": 0
        },
        {
          "discountRate": 0,
          "levelLimit": 0,
          "mesoPrice": 42000,
          "period": 0,
          "templateId": 1041042,
          "tokenPrice": 0,
          "tokenTemplateId": 0
        },
        {
          "discountRate": 0,
          "levelLimit": 0,
          "mesoPrice": 42000,
          "period": 0,
          "templateId": 1041043,
          "tokenPrice": 0,
          "tokenTemplateId": 0
        },
        {
          "discountRate": 0,
          "levelLimit": 0,
          "mesoPrice": 40000,
          "period": 0,
          "templateId": 1050003,
          "tokenPrice": 0,
          "tokenTemplateId": 0
        },
        {
          "discountRate": 0,
          "levelLimit": 0,
          "mesoPrice": 40000,
          "period": 0,
          "templateId": 1050026,
          "tokenPrice": 0,
          "tokenTemplateId": 0
        },
        {
          "discountRate": 0,
          "levelLimit": 0,
          "mesoPrice": 40000,
          "period": 0,
          "templateId": 1050027,
          "tokenPrice": 0,
          "tokenTemplateId": 0
        },
        {
          "discountRate": 0,
          "levelLimit": 0,
          "mesoPrice": 40000,
          "period": 0,
          "templateId": 1050028,
          "tokenPrice": 0,
          "tokenTemplateId": 0
        },
        {
          "discountRate": 0,
          "levelLimit": 0,
          "mesoPrice": 40000,
          "period": 0,
          "templateId": 1061034,
          "tokenPrice": 0,
          "tokenTemplateId": 0
        },
        {
          "discountRate": 0,
          "levelLimit": 0,
          "mesoPrice": 40000,
          "period": 0,
          "templateId": 1061035,
          "tokenPrice": 0,
          "tokenTemplateId": 0
        },
        {
          "discountRate": 0,
          "levelLimit": 0,
          "mesoPrice": 40000,
          "period": 0,
          "templateId": 1061036,
          "tokenPrice": 0,
          "tokenTemplateId": 0
        },
        {
          "discountRate": 0,
          "levelLimit": 0,
          "mesoPrice": 30000,
          "period": 0,
          "templateId": 1002161,
          "tokenPrice": 0,
          "tokenTemplateId": 0
        },
        {
          "discountRate": 0,
          "levelLimit": 0,
          "mesoPrice": 30000,
          "period": 0,
          "templateId": 1002162,
          "tokenPrice": 0,
          "tokenTemplateId": 0
        },
        {
          "discountRate": 0,
          "levelLimit": 0,
          "mesoPrice": 30000,
          "period": 0,
          "templateId": 1002163,
          "tokenPrice": 0,
          "tokenTemplateId": 0
        },
        {
          "discountRate": 0,
          "levelLimit": 0,
          "mesoPrice": 30000,
          "period": 0,
          "templateId": 1002164,
          "tokenPrice": 0,
          "tokenTemplateId": 0
        },
        {
          "discountRate": 0,
          "levelLimit": 0,
          "mesoPrice": 30000,
          "period": 0,
          "templateId": 1002165,
          "tokenPrice": 0,
          "tokenTemplateId": 0
        },
        {
          "discountRate": 0,
          "levelLimit": 0,
          "mesoPrice": 50000,
          "period": 0,
          "templateId": 1040069,
          "tokenPrice": 0,
          "tokenTemplateId": 0
        },
        {
          "discountRate": 0,
          "levelLimit": 0,
          "mesoPrice": 50000,
          "period": 0,
          "templateId": 1040070,
          "tokenPrice": 0,
          "tokenTemplateId": 0
        },
        {
          "discountRate": 0,
          "levelLimit": 0,
          "mesoPrice": 50000,
          "period": 0,
          "templateId": 1040067,
          "tokenPrice": 0,
          "tokenTemplateId": 0
        },
        {
          "discountRate": 0,
          "levelLimit": 0,
          "mesoPrice": 50000,
          "period": 0,
          "templateId": 1040068,
          "tokenPrice": 0,
          "tokenTemplateId": 0
        },
        {
          "discountRate": 0,
          "levelLimit": 0,
          "mesoPrice": 50000,
          "period": 0,
          "templateId": 1041056,
          "tokenPrice": 0,
          "tokenTemplateId": 0
        },
        {
          "discountRate": 0,
          "levelLimit": 0,
          "mesoPrice": 50000,
          "period": 0,
          "templateId": 1041054,
          "tokenPrice": 0,
          "tokenTemplateId": 0
        },
        {
          "discountRate": 0,
          "levelLimit": 0,
          "mesoPrice": 50000,
          "period": 0,
          "templateId": 1041055,
          "tokenPrice": 0,
          "tokenTemplateId": 0
        },
        {
          "discountRate": 0,
          "levelLimit": 0,
          "mesoPrice": 44000,
          "period": 0,
          "templateId": 1060059,
          "tokenPrice": 0,
          "tokenTemplateId": 0
        },
        {
          "discountRate": 0,
          "levelLimit": 0,
          "mesoPrice": 44000,
          "period": 0,
          "templateId": 1060058,
          "tokenPrice": 0,
          "tokenTemplateId": 0
        },
        {
          "discountRate": 0,
          "levelLimit": 0,
          "mesoPrice": 44000,
          "period": 0,
          "templateId": 1060056,
          "tokenPrice": 0,
          "tokenTemplateId": 0
        },
        {
          "discountRate": 0,
          "levelLimit": 0,
          "mesoPrice": 44000,
          "period": 0,
          "templateId": 1060057,
          "tokenPrice": 0,
          "tokenTemplateId": 0
        },
        {
          "discountRate": 0,
          "levelLimit": 0,
          "mesoPrice": 44000,
          "period": 0,
          "templateId": 1061052,
          "tokenPrice": 0,
          "tokenTemplateId": 0
        },
        {
          "discountRate": 0,
          "levelLimit": 0,
          "mesoPrice": 44000,
          "period": 0,
          "templateId": 1061050,
          "tokenPrice": 0,
          "tokenTemplateId": 0
        },
        {
          "discountRate": 0,
          "levelLimit": 0,
          "mesoPrice": 44000,
          "period": 0,
          "templateId": 1061051,
          "tokenPrice": 0,
          "tokenTemplateId": 0
        },
        {
          "discountRate": 0,
          "levelLimit": 0,
          "mesoPrice": 30000,
          "period": 0,
          "templateId": 1002171,
          "tokenPrice": 0,
          "tokenTemplateId": 0
        },
        {
          "discountRate": 0,
          "levelLimit": 0,
          "mesoPrice": 30000,
          "period": 0,
          "templateId": 1002172,
          "tokenPrice": 0,
          "tokenTemplateId": 0
        },
        {
          "discountRate": 0,
          "levelLimit": 0,
          "mesoPrice": 30000,
          "period": 0,
          "templateId": 1002173,
          "tokenPrice": 0,
          "tokenTemplateId": 0
        },
        {
          "discountRate": 0,
          "levelLimit": 0,
          "mesoPrice": 30000,
          "period": 0,
          "templateId": 1002174,
          "tokenPrice": 0,
          "tokenTemplateId": 0
        },
        {
          "discountRate": 0,
          "levelLimit": 0,
          "mesoPrice": 30000,
          "period": 0,
          "templateId": 1002175,
          "tokenPrice": 0,
          "tokenTemplateId": 0
        },
        {
          "discountRate": 0,
          "levelLimit": 0,
          "mesoPrice": 45000,
          "period": 0,
          "templateId": 1040057,
          "tokenPrice": 0,
          "tokenTemplateId": 0
        },
        {
          "discountRate": 0,
          "levelLimit": 0,
          "mesoPrice": 45000,
          "period": 0,
          "templateId": 1040058,
          "tokenPrice": 0,
          "tokenTemplateId": 0
        },
        {
          "discountRate": 0,
          "levelLimit": 0,
          "mesoPrice": 45000,
          "period": 0,
          "templateId": 1040059,
          "tokenPrice": 0,
          "tokenTemplateId": 0
        },
        {
          "discountRate": 0,
          "levelLimit": 0,
          "mesoPrice": 45000,
          "period": 0,
          "templateId": 1040060,
          "tokenPrice": 0,
          "tokenTemplateId": 0
        },
        {
          "discountRate": 0,
          "levelLimit": 0,
          "mesoPrice": 45000,
          "period": 0,
          "templateId": 1041047,
          "tokenPrice": 0,
          "tokenTemplateId": 0
        },
        {
          "discountRate": 0,
          "levelLimit": 0,
          "mesoPrice": 45000,
          "period": 0,
          "templateId": 1041048,
          "tokenPrice": 0,
          "tokenTemplateId": 0
        },
        {
          "discountRate": 0,
          "levelLimit": 0,
          "mesoPrice": 45000,
          "period": 0,
          "templateId": 1041049,
          "tokenPrice": 0,
          "tokenTemplateId": 0
        },
        {
          "discountRate": 0,
          "levelLimit": 0,
          "mesoPrice": 45000,
          "period": 0,
          "templateId": 1041050,
          "tokenPrice": 0,
          "tokenTemplateId": 0
        },
        {
          "discountRate": 0,
          "levelLimit": 0,
          "mesoPrice": 40000,
          "period": 0,
          "templateId": 1060043,
          "tokenPrice": 0,
          "tokenTemplateId": 0
        },
        {
          "discountRate": 0,
          "levelLimit": 0,
          "mesoPrice": 40000,
          "period": 0,
          "templateId": 1060044,
          "tokenPrice": 0,
          "tokenTemplateId": 0
        },
        {
          "discountRate": 0,
          "levelLimit": 0,
          "mesoPrice": 40000,
          "period": 0,
          "templateId": 1060045,
          "tokenPrice": 0,
          "tokenTemplateId": 0
        },
        {
          "discountRate": 0,
          "levelLimit": 0,
          "mesoPrice": 40000,
          "period": 0,
          "templateId": 1060046,
          "tokenPrice": 0,
          "tokenTemplateId": 0
        },
        {
          "discountRate": 0,
          "levelLimit": 0,
          "mesoPrice": 40000,
          "period": 0,
          "templateId": 1061043,
          "tokenPrice": 0,
          "tokenTemplateId": 0
        },
        {
          "discountRate": 0,
          "levelLimit": 0,
          "mesoPrice": 40000,
          "period": 0,
          "templateId": 1061044,
          "tokenPrice": 0,
          "tokenTemplateId": 0
        },
        {
          "discountRate": 0,
          "levelLimit": 0,
          "mesoPrice": 40000,
          "period": 0,
          "templateId": 1061045,
          "tokenPrice": 0,
          "tokenTemplateId": 0
        },
        {
          "discountRate": 0,
          "levelLimit": 0,
          "mesoPrice": 40000,
          "period": 0,
          "templateId": 1061046,
          "tokenPrice": 0,
          "tokenTemplateId": 0
        },
        {
          "discountRate": 0,
          "levelLimit": 0,
          "mesoPrice": 40000,
          "period": 0,
          "templateId": 1002622,
          "tokenPrice": 0,
          "tokenTemplateId": 0
        },
        {
          "discountRate": 0,
          "levelLimit": 0,
          "mesoPrice": 90000,
          "period": 0,
          "templateId": 1052107,
          "tokenPrice": 0,
          "tokenTemplateId": 0
        }
      ],
      "npcId": 2012004,
      "recharger": false
    },
    "id": "2.012004e+06",
    "type": "npc-shop"
  }
}
