{
  "WriterName": "StatusMessageUpdateQuestRecord",
  "IDAName": "CWvsContext::OnMessage#UpdateQuestRecord",
  "Address": "0x843bd8",
  "Variant": "GMS/v61",
  "BranchDepth": 0,
  "AtlasFile": "libs/atlas-packet/character/clientbound/status_message.go",
  "Rows": [
    {
      "Index": 0,
      "AtlasOp": 0,
      "AtlasKind": 0,
      "IDAOp": 1,
      "IDAComment": "questId @0x919627",
      "Verdict": 2,
      "Note": "width mismatch"
    },
    {
      "Index": 1,
      "AtlasOp": 1,
      "AtlasKind": 0,
      "IDAOp": 0,
      "IDAComment": "subtype 1 @0x919638",
      "Verdict": 2,
      "Note": "width mismatch"
    },
    {
      "Index": 2,
      "AtlasOp": 0,
      "AtlasKind": 0,
      "IDAOp": 4,
      "IDAComment": "info @0x9196fa",
      "Verdict": 2,
      "Note": "width mismatch"
    },
    {
      "Index": 3,
      "AtlasOp": 4,
      "AtlasKind": 0,
      "IDAOp": 0,
      "IDAComment": "",
      "Verdict": 2,
      "Note": "atlas: extra — client never reads this field"
    }
  ],
  "Verdict": 2,
  "FlatInvalid": false
}